qypi/__init__.py
qypi/__main__.py
qypi/api.py
qypi/util.py
qypi-0.6.1.dist-info/METADATA
qypi-0.6.1.dist-info/WHEEL
qypi-0.6.1.dist-info/entry_points.txt
qypi-0.6.1.dist-info/licenses/LICENSE
qypi-0.6.1.dist-info/RECORD
