Metadata-Version: 2.4
Name: qypi
Version: 0.6.1
Summary: Query PyPI from the command line
Project-URL: Source Code, https://github.com/jwodder/qypi
Project-URL: Bug Tracker, https://github.com/jwodder/qypi/issues
Author-email: John Thorvald Wodder II <qypi@varonathe.org>
License-Expression: MIT
License-File: LICENSE
Keywords: packages,pip,pypi,search,warehouse
Classifier: Environment :: Console
Classifier: Intended Audience :: Developers
Classifier: Intended Audience :: Information Technology
Classifier: Programming Language :: Python :: 3
Classifier: Programming Language :: Python :: 3 :: Only
Classifier: Programming Language :: Python :: 3.10
Classifier: Programming Language :: Python :: 3.11
Classifier: Programming Language :: Python :: 3.12
Classifier: Programming Language :: Python :: 3.13
Classifier: Programming Language :: Python :: Implementation :: CPython
Classifier: Programming Language :: Python :: Implementation :: PyPy
Classifier: Topic :: Software Development :: Libraries :: Python Modules
Classifier: Topic :: System :: Software Distribution
Requires-Python: >=3.10
Requires-Dist: click!=8.2.2,~=8.2
Requires-Dist: packaging>=16
Requires-Dist: requests~=2.20
